LICENSE.txt
MANIFEST.in
README.md
setup.py
blochsimu/__init__.py
blochsimu/_bloch.py
blochsimu/bloch.py
blochsimu.egg-info/PKG-INFO
blochsimu.egg-info/SOURCES.txt
blochsimu.egg-info/dependency_links.txt
blochsimu.egg-info/not-zip-safe
blochsimu.egg-info/requires.txt
blochsimu.egg-info/top_level.txt