Metadata-Version: 1.1
Name: blochsimu
Version: 0.1.2
Summary: Bloch equation simulator for e.g. NMR-related simulations
Home-page: http://github.com/k7hoven/blochsimu
Author: Koos C.J. Zevenhoven
Author-email: koos.zevenhoven@aalto.fi
License: BSD
Platform: UNKNOWN
Classifier: Development Status :: 4 - Beta
Classifier: License :: OSI Approved :: BSD License
Classifier: Programming Language :: Python :: 3
Classifier: Programming Language :: Python :: 2.7
Classifier: Topic :: Scientific/Engineering :: Physics
Classifier: Topic :: Scientific/Engineering :: Medical Science Apps.
Classifier: Topic :: Scientific/Engineering :: Mathematics
